tf_utilities/__init__.py
tf_utilities/config.py
tf_utilities/data.py
tf_utilities/devices.py
tf_utilities/scripting.py
tf_utilities/strategy.py
tf_utilities/subbatching.py
tf_utilities/utils.py
tf_utilities-0.1.9.dist-info/LICENSE
tf_utilities-0.1.9.dist-info/METADATA
tf_utilities-0.1.9.dist-info/WHEEL
tf_utilities-0.1.9.dist-info/top_level.txt
tf_utilities-0.1.9.dist-info/RECORD
