Metadata-Version: 2.1
Name: tf-utilities
Version: 0.1.9
Summary: A light-weight library of utilities for TensorFlow 2/Keras.
Author-email: David Ludwig <davidludwigii@gmail.com>
License: Copyright (c) 2012-2022 Scott Chacon and others
Project-URL: Homepage, https://github.com/DLii-Research/tf-utilities
Project-URL: Bug Tracker, https://github.com/DLii-Research/tf-utilities/issues
Classifier: Programming Language :: Python :: 3
Classifier: License :: OSI Approved :: MIT License
Classifier: Operating System :: OS Independent
Requires-Python: >=3.7
License-File: LICENSE
Requires-Dist: lmdbm-lockable (>=0.0.5)
